reddwarfclient
