Metadata-Version: 1.0
Name: python-reddwarfclient
Version: 0.1.2
Summary: Rich client bindings for Reddwarf REST API.
Home-page: https://github.com/stackforge/python-reddwarfclient
Author: OpenStack
Author-email: UNKNOWN
License: Apache License, Version 2.0
Platform: UNKNOWN
Classifier: Development Status :: 5 - Production/Stable
Classifier: Environment :: Console
Classifier: Intended Audience :: Developers
Classifier: Intended Audience :: Information Technology
Classifier: License :: OSI Approved :: Apache Software License
Classifier: Operating System :: OS Independent
Classifier: Programming Language :: Python
